README.md
setup.py
src/pyDataMover/__init__.py
src/pyDataMover/_pyDataMover.cpp
src/pyDataMover/errors.py
src/pyDataMover/route.py
src/pyDataMover/server.py
src/pyDataMover/utils.py
src/pyDataMover.egg-info/PKG-INFO
src/pyDataMover.egg-info/SOURCES.txt
src/pyDataMover.egg-info/dependency_links.txt
src/pyDataMover.egg-info/not-zip-safe
src/pyDataMover.egg-info/requires.txt
src/pyDataMover.egg-info/top_level.txt
src/pyDataMover/movers/__init__.py
src/pyDataMover/movers/file_file.py
src/pyDataMover/movers/file_s3.py
src/pyDataMover/movers/file_wdt.py
src/pyDataMover/movers/mover.py
src/pyDataMover/movers/wdt_file.py