Metadata-Version: 1.0
Name: pyDataMover
Version: 0.0.2
Summary: Python wrapper for the Facebook wdt library.
Home-page: https://github.com/majoros/pyDataMover
Author: Chris Majoros
Author-email: chris@majoros.us
License: UNKNOWN
Platform: UNKNOWN
